perse/__init__.py
perse/__main__.py
perse/models.py
perse/perse.py
perse/perse.pyi
perse/utils.py
perse/utils_test.py
perse/version.py
zf_perse-2.3.1.dist-info/LICENSE
zf_perse-2.3.1.dist-info/METADATA
zf_perse-2.3.1.dist-info/WHEEL
zf_perse-2.3.1.dist-info/entry_points.txt
zf_perse-2.3.1.dist-info/top_level.txt
zf_perse-2.3.1.dist-info/RECORD
