Metadata-Version: 2.1
Name: zf-perse
Version: 2.3.1
Summary: perse converts HTML content into structured JSON data
Author: Zeff Muks
Author-email: zeffmuks@gmail.com
License: MIT
License-File: LICENSE
Requires-Dist: beautifulsoup4>=4.12.3
Requires-Dist: loguru>=0.7.2
Requires-Dist: openai>=1.44.0
Requires-Dist: playwright>=1.47.0
Requires-Dist: pydantic>=2.7.4
